call_graph/__init__.py
call_graph/__main__.py
call_graph-0.1.0.dist-info/LICENSE
call_graph-0.1.0.dist-info/METADATA
call_graph-0.1.0.dist-info/WHEEL
call_graph-0.1.0.dist-info/entry_points.txt
call_graph-0.1.0.dist-info/RECORD
