Metadata-Version: 2.1
Name: call-graph
Version: 0.1.0
Summary: `call-graph` is a package for viewing call graph.
Home-page: https://github.com/SaitoTsutomu/call-graph
License: MIT
Author: SaitoTsutomu
Author-email: tsutomu7@hotmail.co.jp
Requires-Python: >=3.12,<4.0
Classifier: Development Status :: 1 - Planning
Classifier: License :: OSI Approved :: MIT License
Classifier: Programming Language :: Python
Classifier: Programming Language :: Python :: 3
Classifier: Programming Language :: Python :: 3.12
Classifier: Topic :: Scientific/Engineering
Classifier: Topic :: Software Development
Requires-Dist: more-itertools (>=10.4,<11.0)
